[
    {
      "src": "public/services/Personalloan.png",
      "title": "Personal Loan"
    },
    {
      "src": "public/services/businessloan.png",
      "title": "Business Loan"
    },
    {
      "src": "public/services/educationloan.png",
      "title": "Education Loan"
    },
    {
      "src": "public/services/homeloan.png",
      "title": "Home Loan"
    },
    {
      "src": "public/services/Supplychain.png",
      "title": "Supply Chain Finance"
    },
    {
      "src": "public/services/Tradefinance.png",
      "title": "Trade Finance"
    }
  ]
  